hella_api/__init__.py
hella_api/hella_api.py
hella_api/manual_methods.py
hella_api-1.1.dist-info/METADATA
hella_api-1.1.dist-info/WHEEL
hella_api-1.1.dist-info/top_level.txt
hella_api-1.1.dist-info/RECORD
