Metadata-Version: 2.1
Name: hella-api
Version: 1.1
Summary: module for api.hella.team
Home-page: https://github.com/tembz/hella_api
Author: tembz
Author-email: ap11dlayt@gmail.com
License: UNKNOWN
Keywords: hella_api
Platform: UNKNOWN
Classifier: Development Status :: 3 - Alpha
Classifier: Intended Audience :: Developers
Classifier: License :: OSI Approved :: MIT License
Classifier: Programming Language :: Python :: 3
Classifier: Programming Language :: Python :: 3.6
Classifier: Programming Language :: Python :: 3.7
Classifier: Programming Language :: Python :: 3.8
Classifier: Programming Language :: Python :: 3.9
Requires-Dist: requests
